MANIFEST.in
README.rst
setup.py
django_mail_dbtpl/__init__.py
django_mail_dbtpl/admin.py
django_mail_dbtpl/models.py
django_mail_dbtpl/utils.py
django_mail_dbtpl.egg-info/PKG-INFO
django_mail_dbtpl.egg-info/SOURCES.txt
django_mail_dbtpl.egg-info/dependency_links.txt
django_mail_dbtpl.egg-info/requires.txt
django_mail_dbtpl.egg-info/top_level.txt
docs/.gitkeep