Metadata-Version: 1.1
Name: django-mail-dbtpl
Version: 0.2.2
Summary: A simple Django app to store email template in database.
Home-page: https://bitbucket.org/crazymath/django-mail-dbtpl
Author: CrazyMath
Author-email: moiseenko.k.s@gmail.com
License: BSD License
Platform: UNKNOWN
Classifier: Environment :: Web Environment
Classifier: Framework :: Django
Classifier: Intended Audience :: Developers
Classifier: License :: OSI Approved :: BSD License
Classifier: Operating System :: OS Independent
Classifier: Programming Language :: Python
Classifier: Programming Language :: Python :: 2.7
Classifier: Topic :: Internet :: WWW/HTTP
Classifier: Topic :: Internet :: WWW/HTTP :: Dynamic Content
